Metadata-Version: 2.1
Name: pywebreport
Version: 0.1.2
Summary: Generates a static html report based on pytest framework
Home-page: https://github.com/yongchin0821/pywebreport
Author: Yongchin
Author-email: yongchin39@qq.com
License: MIT
Project-URL: Bug Tracker, https://github.com/yongchin0821/pywebreport/issues
Keywords: pytest,unittest,htmlreport,reporter,report,pytest report
Platform: UNKNOWN
Classifier: Framework :: Pytest
Classifier: Topic :: Software Development :: Testing
Classifier: Programming Language :: Python
Classifier: Operating System :: OS Independent
Classifier: License :: OSI Approved :: MIT License
Requires-Python: >=3.7
